setup.cfg
setup.py
w2ptemplate/__init__.py
w2ptemplate.egg-info/PKG-INFO
w2ptemplate.egg-info/SOURCES.txt
w2ptemplate.egg-info/dependency_links.txt
w2ptemplate.egg-info/entry_points.txt
w2ptemplate.egg-info/not-zip-safe
w2ptemplate.egg-info/top_level.txt