Metadata-Version: 1.0
Name: w2ptemplate
Version: 1.0.dev0
Summary: Standalone Web2Py template engine
Home-page: https://github.com/KillerGoldFisch/w2ptemplate
Author: Kevin Gliewe
Author-email: kevingliewe@gmail.com
License: UNKNOWN
Keywords: Web2Py Template-engine
Platform: UNKNOWN
